bdsim/__init__.py
bdsim/bdrun.py
bdsim/blockdiagram.py
bdsim/blockdiagram.pyi
bdsim/components.py
bdsim/firmata1.py
bdsim/graphics.py
bdsim/newplots.py
bdsim/run_realtime.py
bdsim/run_sim.py
bdsim/test-stubs.py
bdsim/tex2icon.py
bdsim/bdedit/Icons.py
bdsim/bdedit/__init__.py
bdsim/bdedit/bdedit.py
bdsim/bdedit/block.py
bdsim/bdedit/block_connector_block.py
bdsim/bdedit/block_graphics_block.py
bdsim/bdedit/block_graphics_socket.py
bdsim/bdedit/block_graphics_wire.py
bdsim/bdedit/block_importer.py
bdsim/bdedit/block_main_block.py
bdsim/bdedit/block_param_window.py
bdsim/bdedit/block_socket.py
bdsim/bdedit/block_wire.py
bdsim/bdedit/floating_label.py
bdsim/bdedit/floating_label_graphics.py
bdsim/bdedit/grouping_box.py
bdsim/bdedit/grouping_box_graphics.py
bdsim/bdedit/interface.py
bdsim/bdedit/interface_graphics_scene.py
bdsim/bdedit/interface_graphics_view.py
bdsim/bdedit/interface_manager.py
bdsim/bdedit/interface_scene.py
bdsim/bdedit/interface_scene_history.py
bdsim/bdedit/interface_serialize.py
bdsim/blocks/__init__.py
bdsim/blocks/connections.py
bdsim/blocks/discrete.py
bdsim/blocks/displays.py
bdsim/blocks/functions.py
bdsim/blocks/linalg.py
bdsim/blocks/sinks.py
bdsim/blocks/sources.py
bdsim/blocks/spatial.py
bdsim/blocks/transfers.py
bdsim/blocks/vision.py
bdsim-1.1.2.dist-info/LICENSE
bdsim-1.1.2.dist-info/METADATA
bdsim-1.1.2.dist-info/WHEEL
bdsim-1.1.2.dist-info/entry_points.txt
bdsim-1.1.2.dist-info/top_level.txt
bdsim-1.1.2.dist-info/RECORD
