Metadata-Version: 2.1
Name: bdsim
Version: 1.1.2
Summary: Simulate dynamic systems expressed in block diagram form using Python
Author-email: Peter Corke <rvc@petercorke.com>
License: MIT License
Project-URL: homepage, https://github.com/petercorke/bdsim
Project-URL: documentation, https://petercorke.github.io/bdsim/
Project-URL: repository, https://github.com/petercorke/bdsim
Keywords: python,block diagram,dynamic simulation
Classifier: Programming Language :: Python :: 3 :: Only
Classifier: License :: OSI Approved :: MIT License
Classifier: Operating System :: OS Independent
Requires-Python: >=3.7
License-File: LICENSE
Requires-Dist: numpy>=1.17.4
Requires-Dist: scipy
Requires-Dist: matplotlib
Requires-Dist: spatialmath-python
Requires-Dist: ansitable
Requires-Dist: progress
Provides-Extra: dev
Requires-Dist: sympy; extra == "dev"
Requires-Dist: pytest; extra == "dev"
Requires-Dist: pytest-timeout; extra == "dev"
Requires-Dist: pytest-xvfb; extra == "dev"
Requires-Dist: coverage; extra == "dev"
Requires-Dist: flake8; extra == "dev"
Provides-Extra: docs
Requires-Dist: sphinx; extra == "docs"
Requires-Dist: sphinx-rtd-theme; extra == "docs"
Requires-Dist: sphinx-autorun; extra == "docs"
Requires-Dist: sphinxcontrib-jsmath; extra == "docs"
Requires-Dist: sphinx-markdown-tables; extra == "docs"
Requires-Dist: sphinx-autodoc-typehints; extra == "docs"
Requires-Dist: sphinx-favicon; extra == "docs"
Provides-Extra: edit
Requires-Dist: PyQt5; extra == "edit"
Requires-Dist: PIL; extra == "edit"
